{
  "context-menu": {
    "atom-text-editor": [
      {
        "label": "Toggle The Atom Duck",
        "command": "the-atom-duck:toggle"
      },
      {
        "label": "Close The Atom Duck",
        "command": "the-atom-duck:escape"
      }
    ]
  },
  "menu": [
    {
      "label": "Packages",
      "submenu": [
        {
          "label": "The Atom Duck",
          "submenu": [
            {
              "label": "Toggle",
              "command": "the-atom-duck:toggle"
            },
            {
              "label": "Close",
              "command": "the-atom-duck:escape"
            }
          ]
        }
      ]
    }
  ]
}
